pycalc_sab.py
pycalc_sab-0.0.1.dist-info/METADATA
pycalc_sab-0.0.1.dist-info/WHEEL
pycalc_sab-0.0.1.dist-info/top_level.txt
pycalc_sab-0.0.1.dist-info/RECORD
